include/g2o/config.h
include/g2o/types/sclam2d/odometry_measurement.h
include/g2o/types/sclam2d/edge_se2_sensor_calib.h
include/g2o/types/sclam2d/g2o_types_sclam2d_api.h
include/g2o/types/sclam2d/edge_se2_odom_differential_calib.h
include/g2o/types/sclam2d/vertex_odom_differential_params.h
include/g2o/types/icp/types_icp.h
include/g2o/types/icp/edge_gicp.h
include/g2o/types/icp/g2o_types_icp_api.h
include/g2o/types/sim3/types_seven_dof_expmap.h
include/g2o/types/sim3/types_seven_dof_expmap_api.h
include/g2o/types/sim3/sim3.h
include/g2o/types/slam3d/edge_se3.h
include/g2o/types/slam3d/type_traits_isometry3.h
include/g2o/types/slam3d/isometry3d_mappings.h
include/g2o/types/slam3d/edge_se3_offset.h
include/g2o/types/slam3d/edge_se3_prior.h
include/g2o/types/slam3d/isometry3d_gradients.h
include/g2o/types/slam3d/parameter_camera.h
include/g2o/types/slam3d/edge_se3_lotsofxyz.h
include/g2o/types/slam3d/se3quat.h
include/g2o/types/slam3d/se3_ops.h
include/g2o/types/slam3d/vertex_pointxyz.h
include/g2o/types/slam3d/dquat2mat.h
include/g2o/types/slam3d/edge_xyz_prior.h
include/g2o/types/slam3d/parameter_se3_offset.h
include/g2o/types/slam3d/edge_se3_xyzprior.h
include/g2o/types/slam3d/g2o_types_slam3d_api.h
include/g2o/types/slam3d/edge_se3_pointxyz.h
include/g2o/types/slam3d/edge_se3_pointxyz_depth.h
include/g2o/types/slam3d/vertex_se3.h
include/g2o/types/slam3d/edge_se3_pointxyz_disparity.h
include/g2o/types/slam3d/edge_pointxyz.h
include/g2o/types/slam2d/vertex_se2.h
include/g2o/types/slam2d/edge_se2_pointxy_bearing.h
include/g2o/types/slam2d/edge_se2_pointxy_calib.h
include/g2o/types/slam2d/edge_se2_prior.h
include/g2o/types/slam2d/edge_se2_lotsofxy.h
include/g2o/types/slam2d/g2o_types_slam2d_api.h
include/g2o/types/slam2d/edge_se2_offset.h
include/g2o/types/slam2d/edge_se2_xyprior.h
include/g2o/types/slam2d/edge_pointxy.h
include/g2o/types/slam2d/edge_se2_twopointsxy.h
include/g2o/types/slam2d/vertex_point_xy.h
g2opy-2.2.0.dist-info/RECORD
g2opy-2.2.0.dist-info/WHEEL
g2opy-2.2.0.dist-info/METADATA
g2opy-2.2.0.dist-info/licenses/LICENSE
