Metadata-Version: 2.2
Name: g2opy
Version: 2.2.0
Summary: g2o: A General Framework for Graph Optimization
Author-Email: Rainer Kuemmerle <rainer.kuemmerle@gmail.com>
Requires-Python: >=3.11
